real_time_monitor.abi3.so
real_time_monitor-0.1.9.dist-info/RECORD
real_time_monitor-0.1.9.dist-info/WHEEL
real_time_monitor-0.1.9.dist-info/METADATA
real_time_monitor-0.1.9.dist-info/licenses/LICENSE
real_time_monitor-0.1.9.data/scripts/rtm_gui
real_time_monitor-0.1.9.data/scripts/rtm_recorder
