Metadata-Version: 2.2
Name: real-time-monitor
Version: 0.1.9
Summary: A probe and a moonitor to investigate your application real time behavior.
Maintainer-Email: Philippe Leduc <philippe.leduc@mailfence.com>
License: CeCILL-C
